factory_bo/__init__.py
factory_bo/actions.py
factory_bo/api.py
factory_bo/apps.py
factory_bo/base.py
factory_bo/consts.py
factory_bo/enums.py
factory_bo/exporters.py
factory_bo/factories.py
factory_bo/helpers.py
factory_bo/mixins.py
factory_bo/records.py
factory_bo/settings.py
factory_bo/signals.py
factory_bo/storages.py
factory_bo/strings.py
factory_bo/management/__init__.py
factory_bo/management/commands/__init__.py
factory_bo/management/commands/check_unique_django_get_or_create_fields_set.py
factory_bo/management/commands/collect_dependencies_for_model_records.py
factory_bo/management/commands/collect_factories_django_get_or_create_fields_set.py
factory_bo/management/commands/collect_generated_factories_by_projects.py
factory_bo/management/commands/db_consistency_checker.py
factory_bo/management/commands/find_db_cyclic_relations.py
factory_bo/management/commands/find_fks_without_id_by_projects.py
factory_bo/management/commands/find_self_fk_by_projects.py
factory_bo/management/commands/find_wrong_django_get_or_create_fields.py
factory_bo/management/commands/make_actual_factories_from_default.py
factory_bo/management/commands/make_diff_factories_fixture.py
factory_bo/management/commands/make_factories_for_alone_models.py
factory_bo/management/commands/make_models_fixture.py
factory_bo-0.0.3.dist-info/METADATA
factory_bo-0.0.3.dist-info/WHEEL
factory_bo-0.0.3.dist-info/namespace_packages.txt
factory_bo-0.0.3.dist-info/top_level.txt
factory_bo-0.0.3.dist-info/RECORD
