Metadata-Version: 2.4
Name: factory_bo
Version: 0.0.3
Summary: Electronic Document Management
Home-page: http://docs.budg.bars.group/factory_bo/
Download-URL: 
Author: Stepan Lushchiy
Author-email: s.lushchiy@bars.group
Platform: Any
Classifier: Development Status :: 3 - Alpha
Classifier: License :: OSI Approved :: Apache Software License
Classifier: Programming Language :: Python
Classifier: Programming Language :: Python :: 3
Classifier: Programming Language :: Python :: 3.6
Classifier: Programming Language :: Python :: 3.7
Classifier: Programming Language :: Python :: 3.8
Classifier: Programming Language :: Python :: 3.9
Classifier: Intended Audience :: Developers
Classifier: Environment :: Web Environment
Requires-Dist: parse>=1.18.0
Requires-Dist: Django>=2.2.2
Requires-Dist: factory-boy==2.11.1
Requires-Dist: isort==5.1.4
Dynamic: author
Dynamic: author-email
Dynamic: classifier
Dynamic: description
Dynamic: home-page
Dynamic: platform
Dynamic: requires-dist
Dynamic: summary
